{
    "updated": "2022/06/21",
    "news": [
        {
            "date": "2022/06/21",
            "title": "＜れいにーれにちゃん！お誕生日おめでとう！ ＞『とびだせ！ぐーちょきぱーてぃー』より「ぐーちょき一回きりチャレンジ」を公開！",
            "url": "https://www.momoclo.net/pub/pc/information/?id=7039"
        },
        {
            "date": "2022/06/20",
            "title": "【Movie】「メッセージの向こうから」2022.06.20「MOMOIRO CLOVER Z 6th ALBUM TOUR “祝典” 福岡県 福岡サンパレス",
            "url": "https://www.momoclo.net/pub/pc/information/?id=7038"
        },
        {
            "date": "2022/06/20",
            "title": "＜本日の祝電＞6/20(月)福岡サンパレスDAY2",
            "url": "https://www.momoclo.net/pub/pc/information/?id=6900"
        },
        {
            "date": "2022/06/20",
            "title": "＜佐野市のPRコーナーを映像でお届け！in 祝典ツアー＞6月17日(金)栃木県佐野市",
            "url": "https://www.momoclo.net/pub/pc/information/?id=6918"
        },
        {
            "date": "2022/06/20",
            "title": "＜AE会員先行受付中！～6/22(水)23:59まで！＞「ももクロ夏のバカ騒ぎ2022 -MOMOFEST-」",
            "url": "https://www.momoclo.net/pub/pc/information/?id=7013"
        },
        {
            "date": "2022/06/20",
            "title": "KIND新作「浴衣　変わり市松 CHECKERED PATTERN 」 「頭皮ケアシャンプー ももクロデザインver.」の詰め替えが入荷♪",
            "url": "https://www.momoclo.net/pub/pc/information/?id=7033"
        },
        {
            "date": "2022/06/20",
            "title": "＜当日のしおり＞6/20(月)福岡サンパレス公演「MOMOIRO CLOVER Z 6th ALBUM TOUR “祝典”」【ご入場・注意事項について】",
            "url": "https://www.momoclo.net/pub/pc/information/?id=7030"
        },
        {
            "date": "2022/06/20",
            "title": "＜スケジュール＞06/20(月)～06/26(日)",
            "url": "https://www.momoclo.net/pub/pc/information/?id=7035"
        },
        {
            "date": "2022/06/19",
            "title": "【Movie】「メッセージの向こうから」2022.06.19「MOMOIRO CLOVER Z 6th ALBUM TOUR “祝典” 福岡県 福岡サンパレス",
            "url": "https://www.momoclo.net/pub/pc/information/?id=7036"
        },
        {
            "date": "2022/06/19",
            "title": "【2020年実施を予定していたももクロ夏のパノラマ地獄の各特典付き席をご購入だった会員様へ】",
            "url": "https://www.momoclo.net/pub/pc/information/?id=7034"
        }
    ]
}