{
    "updated": "2026/06/28",
    "news": [
        {
            "date": "2026/06/27",
            "title": "あーりん×前山田健一 タッグが送る 30歳記念ソング『30 STREET!!!』 レコーディングメイキングムービー公開！",
            "url": "https://www.momoclo.net/archives/news/260627_02"
        },
        {
            "date": "2026/06/26",
            "title": "＜申し込みは6/27(土)13:00から＞「ももクロ秋の桃神祭2026」JTBオフィシャルアクセスプラン詳細！",
            "url": "https://www.momoclo.net/archives/news/260627_01"
        },
        {
            "date": "2026/06/26",
            "title": "【佐々木彩夏】7/8(水)開催「福島県浪江町コラボイベント」に出演決定！",
            "url": "https://www.momoclo.net/archives/news/260626_02"
        },
        {
            "date": "2026/06/25",
            "title": "＜6/25(木)情報更新！＞『A-rin Museum』開催決定 & チケット販売開始！",
            "url": "https://www.momoclo.net/archives/news/260611_01"
        },
        {
            "date": "2026/06/25",
            "title": "＜2026年5月号発行！＞AE会員様だけのお楽しみ！「MONTHLY PDF」",
            "url": "https://www.momoclo.net/archives/news/260625_01"
        },
        {
            "date": "2026/06/25",
            "title": "【6/25(木)情報更新：特別配信タイムテーブル更新！】「JAPAN JAM 2026」",
            "url": "https://www.momoclo.net/archives/news/260204_01"
        },
        {
            "date": "2026/06/22",
            "title": "＜スケジュール＞6/22(月)～6/28(日)",
            "url": "https://www.momoclo.net/archives/news/260622_01"
        },
        {
            "date": "2026/06/22",
            "title": "【佐々木彩夏】自身初写真集「ぺろり」2026年10月8日(木) 発売決定！さらに写真集発売記念イベントの開催も発表！",
            "url": "https://www.momoclo.net/archives/news/260622_02"
        },
        {
            "date": "2026/06/21",
            "title": "【Movie】「ライブその後に」 2026.06.21「YATSUI FESTIVAL! 2026」",
            "url": "https://www.momoclo.net/archives/news/260621_02"
        },
        {
            "date": "2026/06/21",
            "title": "【高城れに】『高城れに生誕記念商品2026』受注販売開始！",
            "url": "https://www.momoclo.net/archives/news/260621_01"
        }
    ]
}