{
    "updated": "2022/04/23",
    "news": [
        {
            "date": "2022/04/23",
            "title": "＜座長は“ももクロの若大将”玉井詩織！＞“ももクロ一座”がパワーアップして明治座の舞台に帰ってくる！第2回公演は壮大なスケールで贈る大江戸ミュージカル！",
            "url": "https://www.momoclo.net/pub/pc/information/?id=6874"
        },
        {
            "date": "2022/04/23",
            "title": "＜当日のしおり＞「ももクロ春の一大事2022」",
            "url": "https://www.momoclo.net/pub/pc/information/?id=6869"
        },
        {
            "date": "2022/04/22",
            "title": "＜AEファンド＞「ももクロ春の一大事2022」ステージセット撮影・見学についてのご案内",
            "url": "https://www.momoclo.net/pub/pc/information/?id=6875"
        },
        {
            "date": "2022/04/22",
            "title": "【4/22(金)情報更新】駐車場利用につきまして「『夜桜を見る会〜花火大会〜』in浪江」",
            "url": "https://www.momoclo.net/pub/pc/information/?id=6829"
        },
        {
            "date": "2022/04/22",
            "title": "＜当日券販売決定！＞「ももクロ春の一大事2022」",
            "url": "https://www.momoclo.net/pub/pc/information/?id=6873"
        },
        {
            "date": "2022/04/21",
            "title": "＜4月分公開!!＞玉井詩織 AE会員向けデジタルコンテンツ！",
            "url": "https://www.momoclo.net/pub/pc/information/?id=6872"
        },
        {
            "date": "2022/04/21",
            "title": "＜5/17(火)発売！『祝典』収録楽曲発表映像を毎日公開！＞16曲目は「また逢う日まで」、17曲目は「Closing Session -梨-」に決定！",
            "url": "https://www.momoclo.net/pub/pc/information/?id=6871"
        },
        {
            "date": "2022/04/21",
            "title": "＜【大阪府守口市・愛知県西尾市・栃木県佐野市】のAE先行受付・地元優先チケットは4/22(金)13:00から！＞MOMOIRO CLOVER Z 6th ALBUM TOUR “祝典”",
            "url": "https://www.momoclo.net/pub/pc/information/?id=6850"
        },
        {
            "date": "2022/04/21",
            "title": "【2022/4/21(木)情報更新】＜ファンクラブブース設置決定！＞会場でお得な新規ご入会・会員継続を受付します！さらに、AE会員様限定ゲリラ企画も開催！？「ももクロ春の一大事2022」",
            "url": "https://www.momoclo.net/pub/pc/information/?id=6861"
        },
        {
            "date": "2022/04/20",
            "title": "＜5/17(火)発売！『祝典』収録楽曲発表映像を毎日公開！＞15曲目は新曲「手紙」に決定！",
            "url": "https://www.momoclo.net/pub/pc/information/?id=6864"
        }
    ]
}