{
    "updated": "2026/04/09",
    "news": [
        {
            "date": "2026/04/09",
            "title": "＜一般抽選受付中！～4/13(月)23:59まで＞「東京ももクロランド」",
            "url": "https://www.momoclo.net/archives/news/260409_01"
        },
        {
            "date": "2026/04/08",
            "title": "＜タイムテーブル公開！＞玉井詩織出演『EARLY SUMMER FESTA 2026-Music and Beer-』",
            "url": "https://www.momoclo.net/archives/news/260220_01"
        },
        {
            "date": "2026/04/06",
            "title": "＜スケジュール＞4/6(月)～4/12(日)",
            "url": "https://www.momoclo.net/archives/news/260406_01"
        },
        {
            "date": "2026/04/03",
            "title": "【百田夏菜子】初対談集『この道をゆけば』5月18日（月）発売決定！東京・北海道・大阪でトークショーを開催！",
            "url": "https://www.momoclo.net/archives/news/260403_01"
        },
        {
            "date": "2026/04/01",
            "title": "【Movie】「ライブその後に」2026.04.01「VS.超特急」",
            "url": "https://www.momoclo.net/archives/news/260401_02"
        },
        {
            "date": "2026/04/01",
            "title": "【IC会員証】を紛失された会員様へのご案内：「東京ももクロランド」",
            "url": "https://www.momoclo.net/archives/news/260401_01"
        },
        {
            "date": "2026/04/01",
            "title": "玉井詩織インタビュー掲載！「MONTHLY AE」3月号",
            "url": "https://www.momoclo.net/archives/news/260331_1"
        },
        {
            "date": "2026/03/30",
            "title": "【高城れに】ソロコンサートツアー「OTOGIMASHOW」ライブBlu-rayが本日より予約スタート！さらにライブ映像「おとぎましょう」YouTube公開！",
            "url": "https://www.momoclo.net/archives/news/260330_02"
        },
        {
            "date": "2026/03/30",
            "title": "＜スケジュール＞3/30(月)～4/5(日)",
            "url": "https://www.momoclo.net/archives/news/260330_01"
        },
        {
            "date": "2026/03/29",
            "title": "【Audio】「舞台その後に」2026.03.29 百田夏菜子「9でカタがつく」千秋楽公演",
            "url": "https://www.momoclo.net/archives/news/260329_01"
        }
    ]
}