{
    "updated": "2021/03/05",
    "news": [
        {
            "date": "2021/03/05",
            "title": "「田中将大MTXIX × ニューエラ × ニューヨーク・ヤンキース × 野口強」 コラボグッズからももクロバージョン販売決定！",
            "url": "https://www.momoclo.net/pub/pc/information/?id=6167"
        },
        {
            "date": "2021/03/03",
            "title": "＜佐々木彩夏プロデュース＞『浪江女子発組合』のオフィシャルYouTubeチャンネル開設！さらに、浪江町を訪れた際のオフショット映像を公開！",
            "url": "https://www.momoclo.net/pub/pc/information/?id=6165"
        },
        {
            "date": "2021/03/03",
            "title": "＜返金2次受付をご希望の方へ＞ももいろクローバーZ「3600セカンズ」",
            "url": "https://www.momoclo.net/pub/pc/information/?id=6161"
        },
        {
            "date": "2021/03/03",
            "title": "【3/3(水)情報更新：販売に関するお詫びとお知らせ】＜3/9(火)〜3/11(木)開催！＞「まるごとれにちゃん0202スプリングツアー2020」振替公演グッズ販売について",
            "url": "https://www.momoclo.net/pub/pc/information/?id=6160"
        },
        {
            "date": "2021/03/02",
            "title": "【MSRS新型コロナウイルス感染拡大防止対策ガイドラインを公開いたしました】「まるごとれにちゃん0202スプリングツアー2021」",
            "url": "https://www.momoclo.net/pub/pc/information/?id=6163"
        },
        {
            "date": "2021/03/01",
            "title": "「『ももクロChan』10周年記念プロジェクト　2代目衣装つなぎレプリカ」ご注文殺到による発送遅延のお詫びとお知らせ",
            "url": "https://www.momoclo.net/pub/pc/information/?id=6159"
        },
        {
            "date": "2021/03/01",
            "title": "＜当日券のご案内＞高城れに「まるごとれにちゃん0202スプリングツアー2021」",
            "url": "https://www.momoclo.net/pub/pc/information/?id=6158"
        },
        {
            "date": "2021/03/01",
            "title": "＜スケジュール＞03/01(月) ～ 03/07(日)",
            "url": "https://www.momoclo.net/pub/pc/information/?id=6156"
        },
        {
            "date": "2021/02/28",
            "title": "百田夏菜子インタビュー掲載！「MONTHLY AE」2月号",
            "url": "https://www.momoclo.net/pub/pc/information/?id=6157"
        },
        {
            "date": "2021/02/24",
            "title": "＜2/24(水)発売！ニューアルバム『田中将大』＞未公開LIVE映像大放出祭にて限定公開されていたLIVE映像4本を一挙公開！",
            "url": "https://www.momoclo.net/pub/pc/information/?id=6155"
        }
    ]
}