{
    "updated": "2021/12/09",
    "news": [
        {
            "date": "2021/12/08",
            "title": "【Movie】「ライブその後に」2021.12.8「ももいろクリスマス2021〜さいたまスーパーアリーナ大会〜」",
            "url": "https://www.momoclo.net/pub/pc/information/?id=6650"
        },
        {
            "date": "2021/12/08",
            "title": "＜本日12/8(水)よりWATCHAにて独占配信スタート！＞百田夏菜子出演 映画「すくってごらん」",
            "url": "https://www.momoclo.net/pub/pc/information/?id=6649"
        },
        {
            "date": "2021/12/08",
            "title": "本日12/8(水)DAY2開催！＜当日のしおり＞「ももいろクリスマス2021」【ご入場・注意事項について】",
            "url": "https://www.momoclo.net/pub/pc/information/?id=6640"
        },
        {
            "date": "2021/12/08",
            "title": "＜チケット一般抽選受付は終了しました＞「第5回ももいろ歌合戦～届け！希望の彼方へ～」",
            "url": "https://www.momoclo.net/pub/pc/information/?id=6637"
        },
        {
            "date": "2021/12/07",
            "title": "【Movie】玉さんからの一足早いクリスマスプレゼント",
            "url": "https://www.momoclo.net/pub/pc/information/?id=6648"
        },
        {
            "date": "2021/12/07",
            "title": "「ももいろクリスマス2021」第三回＆第四回オンライン抽選会開催！今回はチャンスが2回♪",
            "url": "https://www.momoclo.net/pub/pc/information/?id=6639"
        },
        {
            "date": "2021/12/07",
            "title": "スターダストプラネット公式動画配信サービス『スタコミュ』リリース決定！！",
            "url": "https://www.momoclo.net/pub/pc/information/?id=6644"
        },
        {
            "date": "2021/12/06",
            "title": "＜DAY1 12/7(火)公演の当日引換券販売が決定！＞「ももいろクリスマス2021 ～さいたまスーパーアリーナ大会～」",
            "url": "https://www.momoclo.net/pub/pc/information/?id=6645"
        },
        {
            "date": "2021/12/06",
            "title": "＜配信決定！＞12/11(土)開催 「2021年JA浪江 組合総会　あいのりきっぷ」",
            "url": "https://www.momoclo.net/pub/pc/information/?id=6621"
        },
        {
            "date": "2021/12/06",
            "title": "＜スケジュール＞12/06(月)～12/12(日)",
            "url": "https://www.momoclo.net/pub/pc/information/?id=6632"
        }
    ]
}