{
    "updated": "2021/06/14",
    "news": [
        {
            "date": "2021/06/14",
            "title": "『玉井詩織生誕記念商品2021』 & NEW「しおりん人形」発売決定！！",
            "url": "https://www.momoclo.net/pub/pc/information/?id=6338"
        },
        {
            "date": "2021/06/14",
            "title": "＜6/30(水)同時発売！「ももクロChan」DVD＆Blu-ray第8弾／「Musée duももクロ」Blu-ray＞はるえ商店限定の映像特典内容が決定！さらに、【映像特典付きセット】を数量限定で6/14(月)21:00より再予約開始！",
            "url": "https://www.momoclo.net/pub/pc/information/?id=6337"
        },
        {
            "date": "2021/06/14",
            "title": "＜本日6/14(月)20:00からWOWOWで放送・配信スタート！＞木梨憲武さんによる新番組「木に梨はなる　～頭の中の大宇宙～」 のナレーション決定！",
            "url": "https://www.momoclo.net/pub/pc/information/?id=6321"
        },
        {
            "date": "2021/06/14",
            "title": "＜スケジュール＞06/14(月) ～ 06/20(日)",
            "url": "https://www.momoclo.net/pub/pc/information/?id=6325"
        },
        {
            "date": "2021/06/14",
            "title": "＜たくさんのご協力ありがとうございました。＞緊急企画！高城れにへの質問を大募集！",
            "url": "https://www.momoclo.net/pub/pc/information/?id=6330"
        },
        {
            "date": "2021/06/13",
            "title": "＜AE2次受付決定！＞佐々木彩夏コンサート「AYAKA NATION 2021」",
            "url": "https://www.momoclo.net/pub/pc/information/?id=6331"
        },
        {
            "date": "2021/06/12",
            "title": "「百田夏菜子 生誕記念商品2021」決定！さらに、百田夏菜子プロデュース『MCZライブ声援ペンライト』も同時受付スタート！",
            "url": "https://www.momoclo.net/pub/pc/information/?id=6336"
        },
        {
            "date": "2021/06/12",
            "title": "百田夏菜子 Birthday BOOK 27 発売決定！申し込みは誕生日の7月12日（月）まで！",
            "url": "https://www.momoclo.net/pub/pc/information/?id=6327"
        },
        {
            "date": "2021/06/12",
            "title": "【Movie】あーりんお誕生日おめでとう♪",
            "url": "https://www.momoclo.net/pub/pc/information/?id=6335"
        },
        {
            "date": "2021/06/11",
            "title": "【6/11(金)営業時間の情報更新】ご好評につき6/30までの期間延長決定！宿泊受付は5/19(水)15:00から！『ももプリ♡2021～春は品プリと新横プリでももクロとコラボだZ～』",
            "url": "https://www.momoclo.net/pub/pc/information/?id=6194"
        }
    ]
}